{"tweetSentenceList":[{"constTree":"(ROOT (S (CC And) (NP (NP (DT the)) (CC and) (NP (NP (DT the) (NN #Sorrow)) (VP (VBN mixed) (PRT (RP up))) (, ,))) (VP (VBZ leads) (SBAR (S (NP (NNP #Mistrust)) (ADVP (RB now)) (NP (PRP it)) (VP (VBZ gets) (ADJP (JJ tough) (S (VP (TO to) (VP (ADVP (RB ever)) (VB #Love) (ADVP (RB again)))))))))) (: ...)))","depTree":"[leads/VBZ cc>And/CC nsubj>[the/DT cc>and/CC conj:and>[#Sorrow/NN det>the/DT acl>[mixed/VBN compound:prt>up/RP] punct>,/,]] nsubj>#Sorrow/NN ccomp>[gets/VBZ nsubj>#Mistrust/NNP advmod>now/RB nsubj>it/PRP xcomp>[tough/JJ xcomp>[#Love/VB mark>to/TO advmod>ever/RB advmod>again/RB]]] punct>.../:]","postags":["CC","DT","CC","DT","NN","VBN","RP",",","VBZ","NNP","RB","PRP","VBZ","JJ","TO","RB","VB","RB",":"]}],"unigrams":["And","the","and","the","#Sorrow","mixed","up",",","leads","#Mistrust","now","it","gets","tough","to","ever","#Love","again","..."],"bigrams":["<s> And","And the","the and","and the","the #Sorrow","#Sorrow mixed","mixed up","up ,",", leads","leads #Mistrust","#Mistrust now","now it","it gets","gets tough","tough to","to ever","ever #Love","#Love again","... <s>"],"lemUnigrams":["and","the","and","the","#sorrow","mix","up",",","lead","#Mistrust","now","it","get","tough","to","ever","#love","again","..."],"lemBigrams":["<s> and","and the","the and","and the","the #sorrow","#sorrow mixed","mix up","up ,",", lead","lead #Mistrust","#mistrust now","now it","it get","get tough","tough to","to ever","ever #love","#love again","... <s>"]}