{"tweetSentenceList":[{"constTree":"(ROOT (FRAG (NP (NP (NNS @variousfruits) (NNS @variousfruits)) (SBAR (S (NP (PRP It)) (VP (VBZ 's) (ADJP (JJ sweet)) (SBAR (WHADVP (WRB how)) (S (NP (NP (PRP$ your) (NN movie)) (VP (VBG watching))) (VP (VBZ is) (ADVP (RB really)) (VP (VBG reflecting) (NP (DT the) (NN holiday) (NN spirit) (JJ #bloodlust) (NN #gore))))))))))))","depTree":"[@variousfruits/NNS compound>@variousfruits/NNS acl:relcl>[sweet/JJ nsubj>It/PRP cop>'s/VBZ ccomp>[reflecting/VBG advmod>how/WRB nsubj>[movie/NN nmod:poss>your/PRP$ acl>watching/VBG] aux>is/VBZ advmod>really/RB dobj>[#gore/NN det>the/DT compound>holiday/NN compound>spirit/NN amod>#bloodlust/JJ]]]]","postags":["NNS","NNS","PRP","VBZ","JJ","WRB","PRP$","NN","VBG","VBZ","RB","VBG","DT","NN","NN","JJ","NN"]}],"unigrams":["@variousfruits","@variousfruits","It","'s","sweet","how","your","movie","watching","is","really","reflecting","the","holiday","spirit","#bloodlust","#gore"],"bigrams":["<s> @variousfruits","@variousfruits @variousfruits","@variousfruits It","It 's","'s sweet","sweet how","how your","your movie","movie watching","watching is","is really","really reflecting","reflecting the","the holiday","holiday spirit","spirit #bloodlust","#gore <s>"],"lemUnigrams":["@variousfruits","@variousfruits","it","be","sweet","how","you","movie","watch","be","really","reflect","the","holiday","spirit","#bloodlust","#gore"],"lemBigrams":["<s> @variousfruits","@variousfruits @variousfruits","@variousfruits it","it be","'s sweet","sweet how","how you","you movie","movie watch","watch be","be really","really reflect","reflect the","the holiday","holiday spirit","spirit #bloodlust","#gore <s>"]}