{"tweetSentenceList":[{"constTree":"(ROOT (S (`` ``) (NP (NN Failure)) (ADVP (RB seldom)) (VP (VBZ stops) (NP (PRP you))) (. .)))","depTree":"[stops/VBZ punct>``/`` nsubj>Failure/NN advmod>seldom/RB dobj>you/PRP punct>./.]","postags":["``","NN","RB","VBZ","PRP","."]},{"constTree":"(ROOT (S (SBAR (WHNP (WDT What)) (S (VP (VBZ stops)))) (NP (PRP you)) (VP (VBZ is) (NP (NP (DT the)) (PP (IN of) (NP (NN failure))))) (. .) ('' '')))","depTree":"[the/DT advcl>[stops/VBZ nsubj>What/WDT] nsubj>you/PRP cop>is/VBZ nmod:of>[failure/NN case>of/IN] punct>./. punct>''/'']","postags":["WDT","VBZ","PRP","VBZ","DT","IN","NN",".","''"]},{"constTree":"(ROOT (PRN (: --) (S (NP (NNP Jack) (NNP Lemmon)) (VP (VBP #quote) (NP (JJ #success) (NN #stress) (NN #anxiety))))))","depTree":"[#quote/VBP punct>--/: nsubj>[Lemmon/NNP compound>Jack/NNP] dobj>[#anxiety/NN amod>#success/JJ compound>#stress/NN]]","postags":[":","NNP","NNP","VBP","JJ","NN","NN"]}],"unigrams":["``","Failure","seldom","stops","you",".","What","stops","you","is","the","of","failure",".","''","--","Jack","Lemmon","#quote","#success","#stress","#anxiety"],"bigrams":["<s> ``","`` Failure","Failure seldom","seldom stops","stops you",". <s>","<s> What","What stops","stops you","you is","is the","the of","of failure","failure .","'' <s>","<s> --","-- Jack","Jack Lemmon","Lemmon #quote","#quote #success","#success #stress","#anxiety <s>"],"lemUnigrams":["``","failure","seldom","stop","you",".","what","stop","you","be","the","of","failure",".","''","--","Jack","Lemmon","#quote","#success","#stress","#anxiety"],"lemBigrams":["<s> ``","`` failure","failure seldom","seldom stop","stop you",". <s>","<s> what","what stop","stop you","you be","be the","the of","of failure","failure .","'' <s>","<s> --","-- Jack","Jack Lemmon","Lemmon #quote","#quote #success","#success #stress","#anxiety <s>"]}