{"tweetSentenceList":[{"constTree":"(ROOT (NP (NP (NP (DT The) (NN moment)) (SBAR (S (NP (PRP you)) (VP (VBP realize) (SBAR (S (NP (PRP you)) (VP (MD ca) (RB n't) (VP (VB get) (NP (PRP him)) (ADVP (IN out) (PP (IN of) (NP (PRP$ your) (NN head)))) (: ...) (SBAR (RB Even) (IN though) (S (S (NP (PRP$ your)) (PP (IN in) (NP (DT a) (JJ perfect) (NN fairytale)))) (CC and) (S (NP (PRP he)) (VP (VBZ 's) (VP (VBN moved) (PP (IN on))))))))))))))) (: ...)))","depTree":"[moment/NN det>The/DT acl:relcl>[realize/VBP nsubj>you/PRP ccomp>[get/VB nsubj>you/PRP aux>ca/MD neg>n't/RB dobj>him/PRP nmod:out_of>[head/NN case>[out/IN mwe>of/IN] nmod:poss>your/PRP$] punct>.../: advcl>[your/PRP$ advmod>Even/RB mark>though/IN dep>[fairytale/NN case>in/IN det>a/DT amod>perfect/JJ] cc>and/CC conj:and>[moved/VBN nsubjpass>he/PRP auxpass>'s/VBZ nmod>on/IN]] advcl>moved/VBN]] punct>.../:]","postags":["DT","NN","PRP","VBP","PRP","MD","RB","VB","PRP","IN","IN","PRP$","NN",":","RB","IN","PRP$","IN","DT","JJ","NN","CC","PRP","VBZ","VBN","IN",":"]}],"unigrams":["The","moment","you","realize","you","ca","n't","get","him","out","of","your","head","...","Even","though","your","in","a","perfect","fairytale","and","he","'s","moved","on","..."],"bigrams":["<s> The","The moment","moment you","you realize","realize you","you ca","ca n't","n't get","get him","him out","out of","of your","your head","head ...","... Even","Even though","though your","your in","in a","a perfect","perfect fairytale","fairytale and","and he","he 's","'s moved","moved on","... <s>"],"lemUnigrams":["the","moment","you","realize","you","can","not","get","he","out","of","you","head","...","even","though","you","in","a","perfect","fairytale","and","he","be","move","on","..."],"lemBigrams":["<s> the","the moment","moment you","you realize","realize you","you can","can not","not get","get he","he out","out of","of you","you head","head ...","... even","even though","though you","you in","in a","a perfect","perfect fairytale","fairytale and","and he","he be","'s move","move on","... <s>"]}