{"tweetSentenceList":[{"constTree":"(ROOT (S (NP (PRP I)) (VP (MD wo) (RB n't) (VP (VB be) (ADJP (JJ able) (S (VP (TO to) (VP (VB sleep) (SBAR (IN because) (S (NP (PRP I)) (VP (VBP know) (SBAR (IN that) (S (PP (JJ due) (TO to) (NP (PRP$ my) (JJ new) (NN assignment))) (, ,) (NP (PRP$ my) (NN pay)) (VP (MD will) (VP (VB be) (ADJP (JJ wrong)) (NP-TMP (RB too) (DT this) (NN month))))))))))))))) (. .)))","depTree":"[able/JJ nsubj>I/PRP aux>wo/MD neg>n't/RB cop>be/VB xcomp>[sleep/VB mark>to/TO advcl>[know/VBP mark>because/IN nsubj>I/PRP ccomp>[wrong/JJ mark>that/IN nmod:due_to>[assignment/NN case>[due/JJ mwe>to/TO] nmod:poss>my/PRP$ amod>new/JJ] punct>,/, nsubj>[pay/NN nmod:poss>my/PRP$] aux>will/MD cop>be/VB nmod:tmod>[month/NN advmod>too/RB det>this/DT]]]] punct>./.]","postags":["PRP","MD","RB","VB","JJ","TO","VB","IN","PRP","VBP","IN","JJ","TO","PRP$","JJ","NN",",","PRP$","NN","MD","VB","JJ","RB","DT","NN","."]}],"unigrams":["I","wo","n't","be","able","to","sleep","because","I","know","that","due","to","my","new","assignment",",","my","pay","will","be","wrong","too","this","month","."],"bigrams":["<s> I","I wo","wo n't","n't be","be able","able to","to sleep","sleep because","because I","I know","know that","that due","due to","to my","my new","new assignment","assignment ,",", my","my pay","pay will","will be","be wrong","wrong too","too this","this month",". <s>"],"lemUnigrams":["I","will","not","be","able","to","sleep","because","I","know","that","due","to","my","new","assignment",",","my","pay","will","be","wrong","too","this","month","."],"lemBigrams":["<s> i","I will","will not","not be","be able","able to","to sleep","sleep because","because I","I know","know that","that due","due to","to my","my new","new assignment","assignment ,",", my","my pay","pay will","will be","be wrong","wrong too","too this","this month",". <s>"]}