{"tweetSentenceList":[{"constTree":"(ROOT (S (S (VP (VBD did) (RB n't) (VP (VB buy) (NP (DT a) (NN wii/zelda)) (NP-TMP (NN today))))) (CC and) (S (NP (NP (DT all)) (SBAR (S (NP (PRP I)) (VP (MD can) (VP (VB think) (ADVP (RB about))))))) (VP (VBZ is) (SBAR (WHADJP (WRB how) (JJ much)) (S (NP (PRP I)) (VP (VBP wan) (S (VP (TO na) (VP (VB play) (ADVP (RB skyward)) (NP (NN sword)))))))))) (. .)))","depTree":"[buy/VB aux>did/VBD neg>n't/RB dobj>[wii/zelda/NN det>a/DT] nmod:tmod>today/NN cc>and/CC conj:and>[is/VBZ nsubj>[all/DT acl:relcl>[think/VB nsubj>I/PRP aux>can/MD advmod>about/RB]] ccomp>[wan/VBP dep>[much/JJ advmod>how/WRB] nsubj>I/PRP xcomp>[play/VB mark>na/TO advmod>skyward/RB dobj>sword/NN]]] punct>./.]","postags":["VBD","RB","VB","DT","NN","NN","CC","DT","PRP","MD","VB","RB","VBZ","WRB","JJ","PRP","VBP","TO","VB","RB","NN","."]},{"constTree":"(ROOT (NP (NN #woeisme)))","depTree":"#woeisme/NN","postags":["NN"]}],"unigrams":["did","n't","buy","a","wii/zelda","today","and","all","I","can","think","about","is","how","much","I","wan","na","play","skyward","sword",".","#woeisme"],"bigrams":["<s> did","did n't","n't buy","buy a","a wii/zelda","wii/zelda today","today and","and all","all I","I can","can think","think about","about is","is how","how much","much I","I wan","wan na","na play","play skyward","skyward sword",". <s>","#woeisme <s>"],"lemUnigrams":["do","not","buy","a","wii/zelda","today","and","all","I","can","think","about","be","how","much","I","wan","na","play","skyward","sword",".","#woeisme"],"lemBigrams":["<s> do","do not","not buy","buy a","a wii/zelda","wii/zelda today","today and","and all","all I","I can","can think","think about","about be","be how","how much","much I","I wan","wan na","na play","play skyward","skyward sword",". <s>","#woeisme <s>"]}