{"tweetSentenceList":[{"constTree":"(ROOT (SINV (ADVP (RB Still)) (VP (VBP have) (RB n't) (VP (VBN gotten))) (NP (NP (NN outta) (NN bed)) (ADVP (RB yet))) (: ...) (. .)))","depTree":"[gotten/VBN advmod>Still/RB aux>have/VBP neg>n't/RB nsubj>[bed/NN compound>outta/NN advmod>yet/RB] punct>.../: punct>./.]","postags":["RB","VBP","RB","VBN","NN","NN","RB",":","."]},{"constTree":"(ROOT (S (NP (NN voice)) (VP (VBZ is) (VP (VBN gone))) (. .)))","depTree":"[gone/VBN nsubjpass>voice/NN auxpass>is/VBZ punct>./.]","postags":["NN","VBZ","VBN","."]},{"constTree":"(ROOT (NP (. .)))","depTree":"./.","postags":["."]},{"constTree":"(ROOT (S (NP (CC &)) (VP (VBP have) (S (VP (TO to) (VP (VB work) (PP (IN in) (NP (DT an) (NN hour))) (PP (IN till) (NP (CD 11) (RB o'clock))))))) (: ...)))","depTree":"[have/VBP nsubj>&/CC xcomp>[work/VB mark>to/TO nmod:in>[hour/NN case>in/IN det>an/DT] nmod:till>[11/CD case>till/IN advmod>o'clock/RB]] punct>.../:]","postags":["CC","VBP","TO","VB","IN","DT","NN","IN","CD","RB",":"]}],"unigrams":["Still","have","n't","gotten","outta","bed","yet","...",".","voice","is","gone",".",".","&","have","to","work","in","an","hour","till","11","o'clock","..."],"bigrams":["<s> Still","Still have","have n't","n't gotten","gotten outta","outta bed","bed yet","yet ...",". <s>","<s> voice","voice is","is gone","gone .",". <s>","<s> &","& have","have to","to work","work in","in an","an hour","hour till","till 11","11 o'clock","... <s>"],"lemUnigrams":["still","have","not","get","outta","bed","yet","...",".","voice","be","go",".",".","&","have","to","work","in","a","hour","till","11","o'clock","..."],"lemBigrams":["<s> still","still have","have not","not get","get outta","outta bed","bed yet","yet ...",". <s>","<s> voice","voice be","be go","go .",". <s>","<s> &","& have","have to","to work","work in","in a","a hour","hour till","till 11","11 o'clock","... <s>"]}