{"tweetSentenceList":[{"constTree":"(ROOT (S (NP (NN @dmoney0044) (NN @devf1sk5) (JJ late) (NN night) (NNS practices)) (VP (VBP are) (NP (NP (DT the) (JJS best)) (SBAR (WHADVP (WRB when)) (S (NP (PRP you)) (VP (VBP realize) (SBAR (IN that) (S (NP (PRP you)) (VP (VBP have) (NP (NP (CD 3) (NN test)) (CC &) (NP (NP (NP (CD 1) (NN quiz)) (SBAR (S (VP (TO to) (VP (VB study) (PP (IN for))))))) (CC &) (NP (NP (PRP it)) (SBAR (S (VP (VBZ 's) (NP (CD 10:00)))))))))))))))) (: ...)))","depTree":"[best/JJS nsubj>[practices/NNS compound>@dmoney0044/NN compound>@devf1sk5/NN amod>late/JJ compound>night/NN] cop>are/VBP det>the/DT acl:relcl>[realize/VBP advmod>when/WRB nsubj>you/PRP ccomp>[have/VBP mark>that/IN nsubj>you/PRP dobj>[test/NN nummod>3/CD cc>&/CC conj:&>[quiz/NN nummod>1/CD acl>[study/VB mark>to/TO nmod>for/IN] cc>&/CC conj:&>[it/PRP acl:relcl>[10:00/CD cop>'s/VBZ]]] conj:&>it/PRP] dobj>quiz/NN]] punct>.../:]","postags":["NN","NN","JJ","NN","NNS","VBP","DT","JJS","WRB","PRP","VBP","IN","PRP","VBP","CD","NN","CC","CD","NN","TO","VB","IN","CC","PRP","VBZ","CD",":"]}],"unigrams":["@dmoney0044","@devf1sk5","late","night","practices","are","the","best","when","you","realize","that","you","have","3","test","&","1","quiz","to","study","for","&","it","'s","10:00","..."],"bigrams":["<s> @dmoney0044","@dmoney0044 @devf1sk5","@devf1sk5 late","late night","night practices","practices are","are the","the best","best when","when you","you realize","realize that","that you","you have","have 3","3 test","test &","& 1","1 quiz","quiz to","to study","study for","for &","& it","it 's","'s 10:00","... <s>"],"lemUnigrams":["@dmoney0044","@devf1sk5","late","night","practice","be","the","best","when","you","realize","that","you","have","3","test","&","1","quiz","to","study","for","&","it","be","10:00","..."],"lemBigrams":["<s> @dmoney0044","@dmoney0044 @devf1sk5","@devf1sk5 late","late night","night practice","practice be","be the","the best","best when","when you","you realize","realize that","that you","you have","have 3","3 test","test &","& 1","1 quiz","quiz to","to study","study for","for &","& it","it be","'s 10:00","... <s>"]}