{"tweetSentenceList":[{"constTree":"(ROOT (S (NP (DT That) (JJ sweet) (NN moment)) (SBAR (WHADVP (WRB when)) (S (NP (DT a) (NN toddler)) (VP (VBZ accepts) (NP (NP (NNP Christ)) (PP (IN as) (NP (PRP$ their) (NN savior))))))) (. .)))","depTree":"[accepts/VBZ dep>[moment/NN det>That/DT amod>sweet/JJ] advmod>when/WRB nsubj>[toddler/NN det>a/DT] dobj>[Christ/NNP nmod:as>[savior/NN case>as/IN nmod:poss>their/PRP$]] punct>./.]","postags":["DT","JJ","NN","WRB","DT","NN","VBZ","NNP","IN","PRP$","NN","."]}],"unigrams":["That","sweet","moment","when","a","toddler","accepts","Christ","as","their","savior","."],"bigrams":["<s> That","That sweet","sweet moment","moment when","when a","a toddler","toddler accepts","accepts Christ","Christ as","as their","their savior",". <s>"],"lemUnigrams":["that","sweet","moment","when","a","toddler","accept","Christ","as","they","savior","."],"lemBigrams":["<s> that","that sweet","sweet moment","moment when","when a","a toddler","toddler accept","accept Christ","Christ as","as they","they savior",". <s>"]}