{"tweetSentenceList":[{"constTree":"(ROOT (S (VP (VB Sick) (PP (IN like) (NP (DT a) (NN dog)))) (. .)))","depTree":"[Sick/VB nmod:like>[dog/NN case>like/IN det>a/DT] punct>./.]","postags":["VB","IN","DT","NN","."]},{"constTree":"(ROOT (NP (NP (NNS Doctors)) (NP (NN tomorrow))))","depTree":"[Doctors/NNS dep>tomorrow/NN]","postags":["NNS","NN"]}],"unigrams":["Sick","like","a","dog",".","Doctors","tomorrow"],"bigrams":["<s> Sick","Sick like","like a","a dog",". <s>","<s> Doctors","tomorrow <s>"],"lemUnigrams":["sick","like","a","dog",".","doctor","tomorrow"],"lemBigrams":["<s> sick","sick like","like a","a dog",". <s>","<s> doctor","tomorrow <s>"]}