{"tweetSentenceList":[{"constTree":"(ROOT (NP (NN Morning) (. .)))","depTree":"[Morning/NN punct>./.]","postags":["NN","."]},{"constTree":"(ROOT (NP (NP (JJ Full) (NN day) (NN conference)) (PP (IN on) (NP (NN insurance) (NN regulation) (NN today)))))","depTree":"[conference/NN amod>Full/JJ compound>day/NN nmod:on>[today/NN case>on/IN compound>insurance/NN compound>regulation/NN]]","postags":["JJ","NN","NN","IN","NN","NN","NN"]}],"unigrams":["Morning",".","Full","day","conference","on","insurance","regulation","today"],"bigrams":["<s> Morning",". <s>","<s> Full","Full day","day conference","conference on","on insurance","insurance regulation","today <s>"],"lemUnigrams":["morning",".","full","day","conference","on","insurance","regulation","today"],"lemBigrams":["<s> morning",". <s>","<s> full","full day","day conference","conference on","on insurance","insurance regulation","today <s>"]}