{"tweetSentenceList":[{"constTree":"(ROOT (S (CC And) (SBAR (RB just) (S (VP (TO to) (VP (VB top) (PRT (RP off)) (NP (NP (DT the) (JJ lovely) (NN mood)) (SBAR (S (NP (PRP I)) (VP (VBP 'm) (PP (IN in)))))))))) (, ,) (NP (PRP we)) (VP (VBP get) (S (VP (TO to) (VP (VB spend) (NP (DT an) (NN hour) (QP (CC and) (DT a) (NN half))) (S (VP (VBG talking) (PP (IN about) (NP (DT the) (NN holocaust)))))))))))","depTree":"[get/VBP cc>And/CC advcl>[top/VB advmod>just/RB mark>to/TO compound:prt>off/RP dobj>[mood/NN det>the/DT amod>lovely/JJ acl:relcl>[in/IN nsubj>I/PRP cop>'m/VBP]]] punct>,/, nsubj>we/PRP xcomp>[spend/VB mark>to/TO dobj>[hour/NN det>an/DT nummod>[half/NN cc>and/CC advmod>a/DT]] xcomp>[talking/VBG nmod:about>[holocaust/NN case>about/IN det>the/DT]]]]","postags":["CC","RB","TO","VB","RP","DT","JJ","NN","PRP","VBP","IN",",","PRP","VBP","TO","VB","DT","NN","CC","DT","NN","VBG","IN","DT","NN"]}],"unigrams":["And","just","to","top","off","the","lovely","mood","I","'m","in",",","we","get","to","spend","an","hour","and","a","half","talking","about","the","holocaust"],"bigrams":["<s> And","And just","just to","to top","top off","off the","the lovely","lovely mood","mood I","I 'm","'m in","in ,",", we","we get","get to","to spend","spend an","an hour","hour and","and a","a half","half talking","talking about","about the","holocaust <s>"],"lemUnigrams":["and","just","to","top","off","the","lovely","mood","I","be","in",",","we","get","to","spend","a","hour","and","a","half","talk","about","the","holocaust"],"lemBigrams":["<s> and","and just","just to","to top","top off","off the","the lovely","lovely mood","mood i","I be","be in","in ,",", we","we get","get to","to spend","spend a","a hour","hour and","and a","a half","half talk","talk about","about the","holocaust <s>"]}