{"tweetSentenceList":[{"constTree":"(ROOT (S (NP (NN Yea) (NN yea)) (NP (PRP I)) (VP (VBP 'm) (ADVP (RB still)) (PP (IN on) (NP (PRP it)))) (. !)))","depTree":"[it/PRP nsubj>[yea/NN compound>Yea/NN] nsubj>I/PRP cop>'m/VBP advmod>still/RB case>on/IN punct>!/.]","postags":["NN","NN","PRP","VBP","RB","IN","PRP","."]},{"constTree":"(ROOT (S (NP (PRP I)) (VP (VBP 'm) (ADVP (RB still)) (VP (VBG grinding))) (. !)))","depTree":"[grinding/VBG nsubj>I/PRP aux>'m/VBP advmod>still/RB punct>!/.]","postags":["PRP","VBP","RB","VBG","."]},{"constTree":"(ROOT (S (VP (VB Sleep) (PP (IN on) (NP (PRP me))) (SBAR (IN if) (S (NP (PRP you)) (VP (VBP want))))) (. !)))","depTree":"[Sleep/VB nmod:on>[me/PRP case>on/IN] advcl>[want/VBP mark>if/IN nsubj>you/PRP] punct>!/.]","postags":["VB","IN","PRP","IN","PRP","VBP","."]},{"constTree":"(ROOT (S (NP (PRP I)) (VP (VBP 'm) (NP (NP (NN comin)) ('' ') (PP (ADVP (IN out)) (IN of) (NP (RB nowhere))))) (. !)))","depTree":"[comin/NN nsubj>I/PRP cop>'m/VBP punct>'/'' nmod:out_of>[nowhere/RB case>[out/IN mwe>of/IN]] punct>!/.]","postags":["PRP","VBP","NN","''","IN","IN","RB","."]},{"constTree":"(ROOT (NP (NN #IknowWHATitIS) (NN #rudeAWAKENING)))","depTree":"[#rudeAWAKENING/NN compound>#IknowWHATitIS/NN]","postags":["NN","NN"]}],"unigrams":["Yea","yea","I","'m","still","on","it","!","I","'m","still","grinding","!","Sleep","on","me","if","you","want","!","I","'m","comin","'","out","of","nowhere","!","#IknowWHATitIS","#rudeAWAKENING"],"bigrams":["<s> Yea","Yea yea","yea I","I 'm","'m still","still on","on it","! <s>","<s> I","I 'm","'m still","still grinding","! <s>","<s> Sleep","Sleep on","on me","me if","if you","you want","! <s>","<s> I","I 'm","'m comin","comin '","' out","out of","of nowhere","! <s>","<s> #IknowWHATitIS","#rudeAWAKENING <s>"],"lemUnigrams":["yea","yea","I","be","still","on","it","!","I","be","still","grind","!","sleep","on","I","if","you","want","!","I","be","comin","'","out","of","nowhere","!","#iknowwhatitis","#rudeawakening"],"lemBigrams":["<s> yea","yea yea","yea i","I be","be still","still on","on it","! <s>","<s> i","I be","be still","still grind","! <s>","<s> Sleep","sleep on","on I","I if","if you","you want","! <s>","<s> i","I be","be comin","comin '","' out","out of","of nowhere","! <s>","<s> #iknowwhatitis","#rudeawakening <s>"]}