{"tweetSentenceList":[{"constTree":"(ROOT (S (NP (NP (DT every) (NN boy)) (PP (IN in) (NP (DT the) (NN basement)))) (VP (VBZ has) (NP (JJ pink) (NN eye)))))","depTree":"[has/VBZ nsubj>[boy/NN det>every/DT nmod:in>[basement/NN case>in/IN det>the/DT]] dobj>[eye/NN amod>pink/JJ]]","postags":["DT","NN","IN","DT","NN","VBZ","JJ","NN"]}],"unigrams":["every","boy","in","the","basement","has","pink","eye"],"bigrams":["<s> every","every boy","boy in","in the","the basement","basement has","has pink","eye <s>"],"lemUnigrams":["every","boy","in","the","basement","have","pink","eye"],"lemBigrams":["<s> every","every boy","boy in","in the","the basement","basement have","have pink","eye <s>"]}