{"tweetSentenceList":[{"constTree":"(ROOT (SINV (FRAG (NP (NP (NNP Cocaphobia)) (PP (IN of) (NP (NP (NN ugliness) (NN aka) (NN prisoner)) (PP (IN of) (NP (NN ugliness) (NN @aalliesun) (NN lmaoo))))))) (VP (VBP love) (S (NP (PRP you)) (ADJP (JJR <)))) (NP (CD 3))))","depTree":"[love/VBP dep>[Cocaphobia/NNP nmod:of>[prisoner/NN case>of/IN compound>ugliness/NN compound>aka/NN nmod:of>[lmaoo/NN case>of/IN compound>ugliness/NN compound>@aalliesun/NN]]] xcomp>[</JJR nsubj>you/PRP] nsubj>3/CD]","postags":["NNP","IN","NN","NN","NN","IN","NN","NN","NN","VBP","PRP","JJR","CD"]}],"unigrams":["Cocaphobia","of","ugliness","aka","prisoner","of","ugliness","@aalliesun","lmaoo","love","you","<","3"],"bigrams":["<s> Cocaphobia","Cocaphobia of","of ugliness","ugliness aka","aka prisoner","prisoner of","of ugliness","ugliness @aalliesun","@aalliesun lmaoo","lmaoo love","love you","you <","3 <s>"],"lemUnigrams":["Cocaphobia","of","ugliness","aka","prisoner","of","ugliness","@aalliesun","lmaoo","love","you","<","3"],"lemBigrams":["<s> cocaphobia","Cocaphobia of","of ugliness","ugliness aka","aka prisoner","prisoner of","of ugliness","ugliness @aalliesun","@aalliesun lmaoo","lmaoo love","love you","you <","3 <s>"]}