{"tweetSentenceList":[{"constTree":"(ROOT (NP (NP (NN lOVE)) (NP (NP (NNP CONQUERz) (NNP All) (NNP WhEThER) (NNP YU) (NNP WAN) (NNP iT)) (SBAR (S (VP (TO TO) (NP (NN OR) (NN NOT)))))) (. .)))","depTree":"[lOVE/NN dep>[iT/NNP compound>CONQUERz/NNP compound>All/NNP compound>WhEThER/NNP compound>YU/NNP compound>WAN/NNP acl>[TO/TO dobj>[NOT/NN compound>OR/NN]]] punct>./.]","postags":["NN","NNP","NNP","NNP","NNP","NNP","NNP","TO","NN","NN","."]},{"constTree":"(ROOT (NP (. .)))","depTree":"./.","postags":["."]},{"constTree":"(ROOT (NP (NP (NN JUZ) (NN liK) (NNP CAN) (NNP bE)) (NP (NP (DT AN) (NNP UNCONTROlAblE) (NN EMOTiON)) (, ,) (NP (NNP SO) (NNP CAN))) (NP (NN #lUV) (CD !!!))))","depTree":"[bE/NNP compound>JUZ/NN compound>liK/NN compound>CAN/NNP dep>[EMOTiON/NN det>AN/DT compound>UNCONTROlAblE/NNP punct>,/, appos>[CAN/NNP compound>SO/NNP]] dep>[#lUV/NN nummod>!!!/CD]]","postags":["NN","NN","NNP","NNP","DT","NNP","NN",",","NNP","NNP","NN","CD"]},{"constTree":"(ROOT (S (NP (-LRB- -LRB-)) (VP (-LRB- -LRB-)) (. .)))","depTree":"[-LRB-/-LRB- nsubj>-LRB-/-LRB- punct>./.]","postags":["-LRB-","-LRB-","."]},{"constTree":"(ROOT (NP (. .)))","depTree":"./.","postags":["."]},{"constTree":"(ROOT (S (NP (NNP YU) (NNP 'VE) (NNP JUZ) (NNP bEEN)) (VP (VBD SERVEd)) (. .)))","depTree":"[SERVEd/VBD nsubj>[bEEN/NNP compound>YU/NNP compound>'VE/NNP compound>JUZ/NNP] punct>./.]","postags":["NNP","NNP","NNP","NNP","VBD","."]},{"constTree":"(ROOT (PRN (. .) (-RRB- -RRB-) (-RRB- -RRB-)))","depTree":"[./. punct>-RRB-/-RRB- punct>-RRB-/-RRB-]","postags":[".","-RRB-","-RRB-"]}],"unigrams":["lOVE","CONQUERz","All","WhEThER","YU","WAN","iT","TO","OR","NOT",".",".","JUZ","liK","CAN","bE","AN","UNCONTROlAblE","EMOTiON",",","SO","CAN","#lUV","!!!","-LRB-","-LRB-",".",".","YU","'VE","JUZ","bEEN","SERVEd",".",".","-RRB-","-RRB-"],"bigrams":["<s> lOVE","lOVE CONQUERz","CONQUERz All","All WhEThER","WhEThER YU","YU WAN","WAN iT","iT TO","TO OR","OR NOT","NOT .",". <s>","<s> JUZ","JUZ liK","liK CAN","CAN bE","bE AN","AN UNCONTROlAblE","UNCONTROlAblE EMOTiON","EMOTiON ,",", SO","SO CAN","CAN #lUV","!!! <s>","<s> -LRB-","-LRB- -LRB-","-LRB- .",". <s>","<s> YU","YU 'VE","'VE JUZ","JUZ bEEN","bEEN SERVEd","SERVEd .",". .",". -RRB-","-RRB- <s>"],"lemUnigrams":["love","CONQUERz","All","WhEThER","YU","WAN","iT","to","or","not",".",".","juz","lik","CAN","bE","a","UNCONTROlAblE","emotion",",","SO","CAN","#luv","!!!","-lrb-","-lrb-",".",".","YU","'VE","JUZ","bEEN","serve",".",".","-rrb-","-rrb-"],"lemBigrams":["<s> love","love conquerz","CONQUERz All","all whether","whether YU","YU WAN","WAN iT","iT to","to or","or not","NOT .",". <s>","<s> juz","juz lik","lik can","CAN be","be a","a uncontrolable","uncontrolable emotion","emotion ,",", SO","SO CAN","CAN #luv","!!! <s>","<s> -lrb-","-lrb- -lrb-","-lrb- .",". <s>","<s> yu","YU ` ve","'ve juz","juz been","been serve","served .",". .",". -rrb-","-rrb- <s>"]}