{"tweetSentenceList":[{"constTree":"(ROOT (S (NP (NN @theweekndxo)) (NP (PRP I)) (VP (VBP love) (NP (NP (NNP House)) (PP (IN of) (NP (NNS balloons))) (, ,) (VP (VBG downloading) (NP-TMP (NNP Thursday)) (SBAR (IN so) (S (NP (PRP I)) (VP (MD can) (VP (VB fall) (ADJP (RB asleep)) (S (VP (VBG listening) (PP (TO to) (NP (PRP it))) (PP (IN on) (NP (PRP$ my) (NN ipod) (NN tonight)))))))))))) (. .)))","depTree":"[love/VBP nsubj>@theweekndxo/NN nsubj>I/PRP dobj>[House/NNP nmod:of>[balloons/NNS case>of/IN] punct>,/, acl>[downloading/VBG nmod:tmod>Thursday/NNP advcl>[fall/VB mark>so/IN nsubj>I/PRP aux>can/MD xcomp>asleep/RB xcomp>[listening/VBG nmod:to>[it/PRP case>to/TO] nmod:on>[tonight/NN case>on/IN nmod:poss>my/PRP$ compound>ipod/NN]]]]] punct>./.]","postags":["NN","PRP","VBP","NNP","IN","NNS",",","VBG","NNP","IN","PRP","MD","VB","RB","VBG","TO","PRP","IN","PRP$","NN","NN","."]}],"unigrams":["@theweekndxo","I","love","House","of","balloons",",","downloading","Thursday","so","I","can","fall","asleep","listening","to","it","on","my","ipod","tonight","."],"bigrams":["<s> @theweekndxo","@theweekndxo I","I love","love House","House of","of balloons","balloons ,",", downloading","downloading Thursday","Thursday so","so I","I can","can fall","fall asleep","asleep listening","listening to","to it","it on","on my","my ipod","ipod tonight",". <s>"],"lemUnigrams":["@theweekndxo","I","love","House","of","balloon",",","download","Thursday","so","I","can","fall","asleep","listen","to","it","on","my","ipod","tonight","."],"lemBigrams":["<s> @theweekndxo","@theweekndxo i","I love","love House","House of","of balloon","balloon ,",", download","download Thursday","Thursday so","so I","I can","can fall","fall asleep","asleep listen","listen to","to it","it on","on my","my ipod","ipod tonight",". <s>"]}