{"tweetSentenceList":[{"constTree":"(ROOT (ADJP (IN about) (S (VP (TO to) (VP (VB shave) (NP (NP (PRP$ my) (NN mug)) (CC and) (NP (PRP$ my) (NN dome))))))))","depTree":"[about/IN xcomp>[shave/VB mark>to/TO dobj>[mug/NN nmod:poss>my/PRP$ cc>and/CC conj:and>[dome/NN nmod:poss>my/PRP$]] dobj>dome/NN]]","postags":["IN","TO","VB","PRP$","NN","CC","PRP$","NN"]}],"unigrams":["about","to","shave","my","mug","and","my","dome"],"bigrams":["<s> about","about to","to shave","shave my","my mug","mug and","and my","dome <s>"],"lemUnigrams":["about","to","shave","my","mug","and","my","dome"],"lemBigrams":["<s> about","about to","to shave","shave my","my mug","mug and","and my","dome <s>"]}