{"tweetSentenceList":[{"constTree":"(ROOT (S (S (VP (VBG Breaking) (NP (NNP News)))) (: ...) (S (NP (NNP Dad) (CC and) (NNP Penny)) (VP (VBP are) (VP (VBG going) (PP (IN on) (NP (NP (DT another) (NN Cruise)) (PP (IN in) (NP (NNP February)))))))) (. .)))","depTree":"[Breaking/VBG dobj>News/NNP punct>.../: parataxis>[going/VBG nsubj>[Dad/NNP cc>and/CC conj:and>Penny/NNP] nsubj>Penny/NNP aux>are/VBP nmod:on>[Cruise/NN case>on/IN det>another/DT nmod:in>[February/NNP case>in/IN]]] punct>./.]","postags":["VBG","NNP",":","NNP","CC","NNP","VBP","VBG","IN","DT","NN","IN","NNP","."]}],"unigrams":["Breaking","News","...","Dad","and","Penny","are","going","on","another","Cruise","in","February","."],"bigrams":["<s> Breaking","Breaking News","News ...","... Dad","Dad and","and Penny","Penny are","are going","going on","on another","another Cruise","Cruise in","in February",". <s>"],"lemUnigrams":["break","News","...","Dad","and","Penny","be","go","on","another","cruise","in","February","."],"lemBigrams":["<s> break","break News","News ...","... Dad","Dad and","and Penny","penny be","be go","go on","on another","another cruise","cruise in","in February",". <s>"]}