{"tweetSentenceList":[{"constTree":"(ROOT (FRAG (NP (DT That) (NN moment)) (SBAR (WHADVP (WRB when)) (S (S (NP (PRP you)) (VP (VBP look) (PP (IN at) (NP (DT the) (NN clock))))) (CC and) (S (NP (PRP it)) (VP (VBZ 's) (ADJP (JJR earlier)) (SBAR (IN than) (S (NP (PRP you)) (VP (VBD thought))))))))))","depTree":"[moment/NN det>That/DT dep>[look/VBP advmod>when/WRB nsubj>you/PRP nmod:at>[clock/NN case>at/IN det>the/DT] cc>and/CC conj:and>[earlier/JJR nsubj>it/PRP cop>'s/VBZ advcl>[thought/VBD mark>than/IN nsubj>you/PRP]]] dep>earlier/JJR]","postags":["DT","NN","WRB","PRP","VBP","IN","DT","NN","CC","PRP","VBZ","JJR","IN","PRP","VBD"]}],"unigrams":["That","moment","when","you","look","at","the","clock","and","it","'s","earlier","than","you","thought"],"bigrams":["<s> That","That moment","moment when","when you","you look","look at","at the","the clock","clock and","and it","it 's","'s earlier","earlier than","than you","thought <s>"],"lemUnigrams":["that","moment","when","you","look","at","the","clock","and","it","be","earlier","than","you","think"],"lemBigrams":["<s> that","that moment","moment when","when you","you look","look at","at the","the clock","clock and","and it","it be","'s earlier","earlier than","than you","think <s>"]}