{"tweetSentenceList":[{"constTree":"(ROOT (S (NP (PRP You)) (VP (VBP know) (S (NP (PRP I)) (VP (VB spend) (NP (NN money)) (SBAR (IN because) (S (NP (NN spending) (NN time)) (VP (VBZ is) (ADJP (JJ hopeless))))))))))","depTree":"[know/VBP nsubj>You/PRP ccomp>[spend/VB nsubj>I/PRP dobj>money/NN advcl>[hopeless/JJ mark>because/IN nsubj>[time/NN compound>spending/NN] cop>is/VBZ]]]","postags":["PRP","VBP","PRP","VB","NN","IN","NN","NN","VBZ","JJ"]}],"unigrams":["You","know","I","spend","money","because","spending","time","is","hopeless"],"bigrams":["<s> You","You know","know I","I spend","spend money","money because","because spending","spending time","time is","hopeless <s>"],"lemUnigrams":["you","know","I","spend","money","because","spending","time","be","hopeless"],"lemBigrams":["<s> you","you know","know I","I spend","spend money","money because","because spending","spending time","time be","hopeless <s>"]}