{"tweetSentenceList":[{"constTree":"(ROOT (FRAG (NP (NP (NNP ITS) (NNP SAD) (NNP HOW) (NNP DEY) (NNP KEEP) (NNP KILLING) (CC &) (NNP MOLESTING) (NNP THESE)) (SBAR (S (NP (NNS CHILDREN)) (VP (VBP !!!)))))))","depTree":"[KILLING/NNP compound>ITS/NNP compound>SAD/NNP compound>HOW/NNP compound>DEY/NNP compound>KEEP/NNP cc>&/CC conj:&>[THESE/NNP compound>MOLESTING/NNP] acl:relcl>[!!!/VBP nsubj>CHILDREN/NNS]]","postags":["NNP","NNP","NNP","NNP","NNP","NNP","CC","NNP","NNP","NNS","VBP"]},{"constTree":"(ROOT (NP (NN SMDH) (NN N)))","depTree":"[N/NN compound>SMDH/NN]","postags":["NN","NN"]}],"unigrams":["ITS","SAD","HOW","DEY","KEEP","KILLING","&","MOLESTING","THESE","CHILDREN","!!!","SMDH","N"],"bigrams":["<s> ITS","ITS SAD","SAD HOW","HOW DEY","DEY KEEP","KEEP KILLING","KILLING &","& MOLESTING","MOLESTING THESE","THESE CHILDREN","!!! <s>","<s> SMDH","N <s>"],"lemUnigrams":["ITS","SAD","HOW","DEY","KEEP","KILLING","&","MOLESTING","THESE","child","!!!","smdh","n"],"lemBigrams":["<s> its","ITS SAD","sad how","HOW DEY","DEY KEEP","keep kill","KILLING &","& MOLESTING","molest these","THESE child","!!! <s>","<s> smdh","n <s>"]}