{"tweetSentenceList":[{"constTree":"(ROOT (NP (NP (NN @Peter__Stifler) (NN ohh)) (NP (NP (NP (NN boy)) (SBAR (WHNP (WDT what)))) (NP (DT a) (JJ great) (NN gift))) (. !)))","depTree":"[ohh/NN compound>@Peter__Stifler/NN dep>[boy/NN acl:relcl>what/WDT dep>[gift/NN det>a/DT amod>great/JJ]] punct>!/.]","postags":["NN","NN","NN","WDT","DT","JJ","NN","."]},{"constTree":"(ROOT (NP (NN stopit) (NN peter)))","depTree":"[peter/NN compound>stopit/NN]","postags":["NN","NN"]}],"unigrams":["@Peter__Stifler","ohh","boy","what","a","great","gift","!","stopit","peter"],"bigrams":["<s> @Peter__Stifler","@Peter__Stifler ohh","ohh boy","boy what","what a","a great","great gift","! <s>","<s> stopit","peter <s>"],"lemUnigrams":["@peter__stifler","ohh","boy","what","a","great","gift","!","stopit","peter"],"lemBigrams":["<s> @peter__stifler","@peter__stifler ohh","ohh boy","boy what","what a","a great","great gift","! <s>","<s> stopit","peter <s>"]}