{"tweetSentenceList":[{"constTree":"(ROOT (S (S (NP (NNP Yo) (NNS cards)) (VP (VBN been) (VP (VBN dealt) (PP (IN in) (NP (NN life)))))) (: ;) (S (S (CC but) (NP (PRP you)) (VP (VBP aint) (NP (NN playem)) (ADVP (RB right)))) (, ,) (NP (NN juss) (NN knowin) (NN u)) (VP (VB let) (VP (VB tuck) (NP (PRP you)) (PP (IN in) (PP (IN at) (NP (NN night)))))))))","depTree":"[dealt/VBN nsubjpass>[cards/NNS compound>Yo/NNP] auxpass>been/VBN nmod:in>[life/NN case>in/IN] punct>;/: parataxis>[let/VB ccomp>[aint/VBP cc>but/CC nsubj>you/PRP dobj>playem/NN advmod>right/RB] punct>,/, nsubj>[u/NN compound>juss/NN compound>knowin/NN] xcomp>[tuck/VB dobj>you/PRP nmod:at>[night/NN case>in/IN case>at/IN]]]]","postags":["NNP","NNS","VBN","VBN","IN","NN",":","CC","PRP","VBP","NN","RB",",","NN","NN","NN","VB","VB","PRP","IN","IN","NN"]}],"unigrams":["Yo","cards","been","dealt","in","life",";","but","you","aint","playem","right",",","juss","knowin","u","let","tuck","you","in","at","night"],"bigrams":["<s> Yo","Yo cards","cards been","been dealt","dealt in","in life","life ;","; but","but you","you aint","aint playem","playem right","right ,",", juss","juss knowin","knowin u","u let","let tuck","tuck you","you in","in at","night <s>"],"lemUnigrams":["Yo","card","be","deal","in","life",";","but","you","aint","playem","right",",","juss","knowin","u","let","tuck","you","in","at","night"],"lemBigrams":["<s> yo","Yo card","card be","be deal","deal in","in life","life ;","; but","but you","you aint","aint playem","playem right","right ,",", juss","juss knowin","knowin u","u let","let tuck","tuck you","you in","in at","night <s>"]}