{"tweetSentenceList":[{"constTree":"(ROOT (S (NP (NP (NN Anything)) (VP (VBN done) (PP (IN OUTSIDE) (NP (NN relationship))) (PP (IN with) (NP (NNP Jesus))))) (VP (VBZ is) (NP (NN religion))) (. .)))","depTree":"[religion/NN nsubj>[Anything/NN acl>[done/VBN nmod:outside>[relationship/NN case>OUTSIDE/IN] nmod:with>[Jesus/NNP case>with/IN]]] cop>is/VBZ punct>./.]","postags":["NN","VBN","IN","NN","IN","NNP","VBZ","NN","."]},{"constTree":"(ROOT (S (VP (VB Live) (PP (IN in) (NP (NP (DT the) (NN midst)) (PP (IN of) (NP (NNP Love)))))) (. .)))","depTree":"[Live/VB nmod:in>[midst/NN case>in/IN det>the/DT nmod:of>[Love/NNP case>of/IN]] punct>./.]","postags":["VB","IN","DT","NN","IN","NNP","."]}],"unigrams":["Anything","done","OUTSIDE","relationship","with","Jesus","is","religion",".","Live","in","the","midst","of","Love","."],"bigrams":["<s> Anything","Anything done","done OUTSIDE","OUTSIDE relationship","relationship with","with Jesus","Jesus is","is religion",". <s>","<s> Live","Live in","in the","the midst","midst of","of Love",". <s>"],"lemUnigrams":["anything","do","outside","relationship","with","Jesus","be","religion",".","live","in","the","midst","of","Love","."],"lemBigrams":["<s> anything","anything do","do outside","outside relationship","relationship with","with Jesus","Jesus be","be religion",". <s>","<s> Live","live in","in the","the midst","midst of","of Love",". <s>"]}