{"tweetSentenceList":[{"constTree":"(ROOT (FRAG (NP-TMP (NP (PRP$ My) (JJ new) (NN job)) (NP (NN description))) (: :) (NP (NP (NNP Housekeeper)) (, ,) (NP (NNP Chef)) (, ,) (NP (NP (NP (NNS Patients)) (NP (NNP Care) (NNP Technician))) (, ,) (CC and) (NP (NP (NP (NN maintenance)) (JJR >)) (NP (CD _) (JJR <)))))))","depTree":"[job/NN nmod:poss>My/PRP$ amod>new/JJ dep>description/NN punct>:/: dep>[Housekeeper/NNP punct>,/, appos>Chef/NNP punct>,/, appos>[Patients/NNS dep>[Technician/NNP compound>Care/NNP] punct>,/, cc>and/CC conj:and>[>/JJR dep>maintenance/NN dep>[</JJR nummod>_/CD]]] appos>>/JJR]]","postags":["PRP$","JJ","NN","NN",":","NNP",",","NNP",",","NNS","NNP","NNP",",","CC","NN","JJR","CD","JJR"]}],"unigrams":["My","new","job","description",":","Housekeeper",",","Chef",",","Patients","Care","Technician",",","and","maintenance",">","_","<"],"bigrams":["<s> My","My new","new job","job description","description :",": Housekeeper","Housekeeper ,",", Chef","Chef ,",", Patients","Patients Care","Care Technician","Technician ,",", and","and maintenance","maintenance >","> _","< <s>"],"lemUnigrams":["my","new","job","description",":","Housekeeper",",","Chef",",","patient","Care","Technician",",","and","maintenance",">","_","<"],"lemBigrams":["<s> my","my new","new job","job description","description :",": housekeeper","Housekeeper ,",", chef","chef ,",", patient","patient Care","Care Technician","technician ,",", and","and maintenance","maintenance >","> _","< <s>"]}