{"tweetSentenceList":[{"constTree":"(ROOT (S (S (VP (VBP Do) (RB n't) (ADVP (RB even)) (VP (VB look) (PP (IN in) (NP (PRP$ his) (NNS eyes)))))) (, ,) (NP (PRP he)) (VP (VP (MD 'll) (VP (VB take) (S (NP (PRP you)) (ADJP (NN nothing))))) (CC but) (VP (VBZ lies))) (. .)))","depTree":"[take/VB ccomp>[look/VB aux>Do/VBP neg>n't/RB advmod>even/RB nmod:in>[eyes/NNS case>in/IN nmod:poss>his/PRP$]] punct>,/, nsubj>he/PRP aux>'ll/MD xcomp>[nothing/NN nsubj>you/PRP] cc>but/CC conj:but>[lies/VBZ nsubj>he/PRP] punct>./.]","postags":["VBP","RB","RB","VB","IN","PRP$","NNS",",","PRP","MD","VB","PRP","NN","CC","VBZ","."]},{"constTree":"(ROOT (S (S (NP (PRP He)) (VP (VBZ looks) (PP (IN like) (NP (NP (DT a) (JJ cool) (NN drink)) (PP (IN of) (NP (NN water))))))) (, ,) (CC but) (S (NP (PRP he)) (VP (VBZ 's) (NP (NN candy) (JJ coated) (NN misery)))) (. .)))","depTree":"[looks/VBZ nsubj>He/PRP nmod:like>[drink/NN case>like/IN det>a/DT amod>cool/JJ nmod:of>[water/NN case>of/IN]] punct>,/, cc>but/CC conj:but>[misery/NN nsubj>he/PRP cop>'s/VBZ compound>candy/NN amod>coated/JJ] punct>./.]","postags":["PRP","VBZ","IN","DT","JJ","NN","IN","NN",",","CC","PRP","VBZ","NN","JJ","NN","."]}],"unigrams":["Do","n't","even","look","in","his","eyes",",","he","'ll","take","you","nothing","but","lies",".","He","looks","like","a","cool","drink","of","water",",","but","he","'s","candy","coated","misery","."],"bigrams":["<s> Do","Do n't","n't even","even look","look in","in his","his eyes","eyes ,",", he","he 'll","'ll take","take you","you nothing","nothing but","but lies",". <s>","<s> He","He looks","looks like","like a","a cool","cool drink","drink of","of water","water ,",", but","but he","he 's","'s candy","candy coated","coated misery",". <s>"],"lemUnigrams":["do","not","even","look","in","he","eye",",","he","will","take","you","nothing","but","lie",".","he","look","like","a","cool","drink","of","water",",","but","he","be","candy","coated","misery","."],"lemBigrams":["<s> do","do not","not even","even look","look in","in he","he eye","eye ,",", he","he ` ll","will take","take you","you nothing","nothing but","but lie",". <s>","<s> he","he look","look like","like a","a cool","cool drink","drink of","of water","water ,",", but","but he","he be","'s candy","candy coat","coated misery",". <s>"]}