{"tweetSentenceList":[{"constTree":"(ROOT (S (NP (DT That) (JJ sad) (NN moment)) (SBAR (WHADVP (WRB when)) (S (NP (FW i)) (VP (VBP do) (RB n't) (VP (VB know) (SBAR (IN that) (S (NP (PRP she)) (VP (VBD lied) (PP (TO to) (NP (PRP me)))))))))) (. .)))","depTree":"[know/VB dep>[moment/NN det>That/DT amod>sad/JJ] advmod>when/WRB nsubj>i/FW aux>do/VBP neg>n't/RB ccomp>[lied/VBD mark>that/IN nsubj>she/PRP nmod:to>[me/PRP case>to/TO]] punct>./.]","postags":["DT","JJ","NN","WRB","FW","VBP","RB","VB","IN","PRP","VBD","TO","PRP","."]},{"constTree":"(ROOT (NP (NN :-LRB-)))","depTree":":-LRB-/NN","postags":["NN"]}],"unigrams":["That","sad","moment","when","i","do","n't","know","that","she","lied","to","me",".",":-LRB-"],"bigrams":["<s> That","That sad","sad moment","moment when","when i","i do","do n't","n't know","know that","that she","she lied","lied to","to me",". <s>",":-LRB- <s>"],"lemUnigrams":["that","sad","moment","when","i","do","not","know","that","she","lie","to","I",".",":-lrb-"],"lemBigrams":["<s> that","that sad","sad moment","moment when","when i","i do","do not","not know","know that","that she","she lie","lie to","to I",". <s>",": -lrb- <s>"]}