{"tweetSentenceList":[{"constTree":"(ROOT (FRAG (S (ADJP (RB expectedly) (JJ unexpected)) (S (NP (NP (NP (NN RT) (NN @EricaKLewis)) (: :) (SBAR (WHADVP (WRB When)) (S (NP (FW u)) (ADVP (RB unexpectedly)) (VP (VB get) (ADJP (JJ drunk)))))) (NP (JJR >)))))))","depTree":"[@EricaKLewis/NN dep>[unexpected/JJ advmod>expectedly/RB] compound>RT/NN punct>:/: acl:relcl>[get/VB advmod>When/WRB nsubj>u/FW advmod>unexpectedly/RB xcomp>drunk/JJ] dep>>/JJR]","postags":["RB","JJ","NN","NN",":","WRB","FW","RB","VB","JJ","JJR"]}],"unigrams":["expectedly","unexpected","RT","@EricaKLewis",":","When","u","unexpectedly","get","drunk",">"],"bigrams":["<s> expectedly","expectedly unexpected","unexpected RT","RT @EricaKLewis","@EricaKLewis :",": When","When u","u unexpectedly","unexpectedly get","get drunk","> <s>"],"lemUnigrams":["expectedly","unexpected","rt","@ericaklewis",":","when","u","unexpectedly","get","drunk",">"],"lemBigrams":["<s> expectedly","expectedly unexpected","unexpected rt","rt @ericaklewis","@EricaKLewis :",": when","when u","u unexpectedly","unexpectedly get","get drunk","> <s>"]}