{"tweetSentenceList":[{"constTree":"(ROOT (FRAG (S (VP (`` ``) (VBZ Is) (NP (NP (PRP$ our) (NN exam)) (SBAR (S (NP (NP (CD 2) (NNS hours)) (CC or) (NP (CD 3)))))))) (. ?) ('' '')))","depTree":"[exam/NN punct>``/`` cop>Is/VBZ nmod:poss>our/PRP$ acl:relcl>[hours/NNS nummod>2/CD cc>or/CC conj:or>3/CD] acl:relcl>3/CD punct>?/. punct>''/'']","postags":["``","VBZ","PRP$","NN","CD","NNS","CC","CD",".","''"]},{"constTree":"(ROOT (NP (NP (NNP Surprise)) (NP (CD 4) (NN hour) (NN case) (NN exam) (NNS #UWOProblems))))","depTree":"[Surprise/NNP dep>[#UWOProblems/NNS nummod>4/CD compound>hour/NN compound>case/NN compound>exam/NN]]","postags":["NNP","CD","NN","NN","NN","NNS"]}],"unigrams":["``","Is","our","exam","2","hours","or","3","?","''","Surprise","4","hour","case","exam","#UWOProblems"],"bigrams":["<s> ``","`` Is","Is our","our exam","exam 2","2 hours","hours or","or 3","3 ?","'' <s>","<s> Surprise","Surprise 4","4 hour","hour case","case exam","#UWOProblems <s>"],"lemUnigrams":["``","be","we","exam","2","hour","or","3","?","''","Surprise","4","hour","case","exam","#uwoproblems"],"lemBigrams":["<s> ``","`` be","be we","we exam","exam 2","2 hour","hour or","or 3","3 ?","'' <s>","<s> Surprise","Surprise 4","4 hour","hour case","case exam","#uwoproblems <s>"]}