{"tweetSentenceList":[{"constTree":"(ROOT (S (NP (PRP I)) (VP (VBP hate) (SBAR (IN that) (S (NP (NP (NN lump)) (SBAR (S (NP (PRP you)) (VP (VBP get) (PP (IN in) (NP (PRP$ your) (NN throat))) (SBAR (WHADVP (WRB when)) (S (NP (PRP you)) (ADVP (RB really)) (VP (VBP wan) (S (VP (TO na) (VP (VB cry) (ADVP (CC but)))))))))))) (VP (VBP do) (RB n't) (VP (VB wan) (S (VP (TO na) (VP (VB let) (NP (PRP it)) (PRT (RP out))))))))))))","depTree":"[hate/VBP nsubj>I/PRP ccomp>[wan/VB mark>that/IN nsubj>[lump/NN acl:relcl>[get/VBP nsubj>you/PRP nmod:in>[throat/NN case>in/IN nmod:poss>your/PRP$] advcl>[wan/VBP advmod>when/WRB nsubj>you/PRP advmod>really/RB xcomp>[cry/VB mark>na/TO advmod>but/CC]]]] aux>do/VBP neg>n't/RB xcomp>[let/VB mark>na/TO dobj>it/PRP compound:prt>out/RP]]]","postags":["PRP","VBP","IN","NN","PRP","VBP","IN","PRP$","NN","WRB","PRP","RB","VBP","TO","VB","CC","VBP","RB","VB","TO","VB","PRP","RP"]}],"unigrams":["I","hate","that","lump","you","get","in","your","throat","when","you","really","wan","na","cry","but","do","n't","wan","na","let","it","out"],"bigrams":["<s> I","I hate","hate that","that lump","lump you","you get","get in","in your","your throat","throat when","when you","you really","really wan","wan na","na cry","cry but","but do","do n't","n't wan","wan na","na let","let it","out <s>"],"lemUnigrams":["I","hate","that","lump","you","get","in","you","throat","when","you","really","wan","na","cry","but","do","not","wan","na","let","it","out"],"lemBigrams":["<s> i","I hate","hate that","that lump","lump you","you get","get in","in you","you throat","throat when","when you","you really","really wan","wan na","na cry","cry but","but do","do not","not wan","wan na","na let","let it","out <s>"]}